pmanager/__init__.py
pmanager/__main__.py
pmanager/add.py
pmanager/add_run.py
pmanager/archive.py
pmanager/changelog
pmanager/changelog.py
pmanager/clone.py
pmanager/config.py
pmanager/delete.py
pmanager/edit_module.py
pmanager/edit_project_conf.py
pmanager/github.py
pmanager/help_func.py
pmanager/import_custom.py
pmanager/open_project.py
pmanager/project_ide.py
pmanager/rename.py
pmanager/res.py
pmanager/run.py
pmanager/share.py
pmanager/show_projects.py
pmanager/terminal.py
pmanager/zip.py
pmanager/modules/__init__.py
pmanager/modules/c++.py
pmanager/modules/c++.xml
pmanager/modules/c.py
pmanager/modules/c.xml
pmanager/modules/flask.py
pmanager/modules/flask.xml
pmanager/modules/node_js.py
pmanager/modules/node_js.xml
pmanager/modules/python.py
pmanager/modules/python.xml
pmanager/modules/__pycache__/__init__.cpython-310.pyc
pmanager/modules/__pycache__/__init__.cpython-38.pyc
pmanager/modules/__pycache__/__init__.cpython-39.pyc
pmanager/modules/__pycache__/python.cpython-39.pyc
projects_manager-0.8.8.3.dist-info/LICENSE
projects_manager-0.8.8.3.dist-info/METADATA
projects_manager-0.8.8.3.dist-info/WHEEL
projects_manager-0.8.8.3.dist-info/entry_points.txt
projects_manager-0.8.8.3.dist-info/top_level.txt
projects_manager-0.8.8.3.dist-info/RECORD
