Metadata-Version: 2.1
Name: projects-manager
Version: 0.8.8.3
Summary: A simple projects manager.
Home-page: https://github.com/ThaaoBlues/pmanager
Author: _ThaaoBlues_
Author-email: thaaoblues81@gmail.com
License: CC BY-NC-ND 4.0
Platform: UNKNOWN
Classifier: License :: Other/Proprietary License
Classifier: Programming Language :: Python
Classifier: Programming Language :: Python :: 3
Classifier: Programming Language :: Python :: 3.10
Requires-Python: >=3.6.0
License-File: LICENSE
Requires-Dist: flask
Requires-Dist: colorama
Requires-Dist: prompt-toolkit
Requires-Dist: distro
Requires-Dist: requests
Requires-Dist: gitpython
